LICENSE.txt
MANIFEST.in
README.md
pyproject.toml
setup.cfg
setup.py
nerfvis/__init__.py
nerfvis/index.html
nerfvis/scene.py
nerfvis/version.py
nerfvis.egg-info/PKG-INFO
nerfvis.egg-info/SOURCES.txt
nerfvis.egg-info/dependency_links.txt
nerfvis.egg-info/top_level.txt
nerfvis/utils/__init__.py
nerfvis/utils/_rotation.c
nerfvis/utils/_rotation.pyx
nerfvis/utils/sh.py