Metadata-Version: 2.1
Name: nerfvis
Version: 0.1.6
Summary: NeRF visualization library
Author: Alex Yu
Author-email: alexyu99126@gmail.com
License-File: LICENSE.txt
